teedoc_plugin_comments_gitalk/__init__.py
teedoc_plugin_comments_gitalk/assets/custom_gitalk.css
teedoc_plugin_comments_gitalk/assets/gitalk.css
teedoc_plugin_comments_gitalk/assets/gitalk.min.js
teedoc_plugin_comments_gitalk/assets/main.js
teedoc_plugin_comments_gitalk-1.5.0.dist-info/LICENSE
teedoc_plugin_comments_gitalk-1.5.0.dist-info/METADATA
teedoc_plugin_comments_gitalk-1.5.0.dist-info/WHEEL
teedoc_plugin_comments_gitalk-1.5.0.dist-info/top_level.txt
teedoc_plugin_comments_gitalk-1.5.0.dist-info/RECORD
