Metadata-Version: 2.1
Name: teedoc-plugin-comments-gitalk
Version: 1.5.0
Summary: gitalk comment plugin for teedoc
Home-page: https://github.com/teedoc/teedoc
Author: Neucrack
Author-email: CZD666666@gmail.com
License: MIT
Keywords: gitalk comment teedoc plugin
Platform: UNKNOWN
Classifier: Intended Audience :: Developers
Classifier: License :: OSI Approved :: MIT License
Classifier: Programming Language :: Python :: 3
